dataframetranslationscoring/__init__.py
dataframetranslationscoring/scoring.py
dataframetranslationscoring/utils.py
dataframetranslationscoring-1.1.dist-info/LICENSE
dataframetranslationscoring-1.1.dist-info/METADATA
dataframetranslationscoring-1.1.dist-info/WHEEL
dataframetranslationscoring-1.1.dist-info/top_level.txt
dataframetranslationscoring-1.1.dist-info/RECORD
